Metadata-Version: 2.1
Name: ppscore
Version: 1.1.1
Summary: Python implementation of the Predictive Power Score (PPS)
Home-page: https://github.com/8080labs/ppscore/
Author: 8080 Labs, Florian Wetschoreck, Tobias Krabel
Author-email: info@8080labs.com
License: mit
Project-URL: Documentation, https://github.com/8080labs/ppscore/
Platform: any
Requires-Python: >=3.6
